import_rewriter/__init__.py
import_rewriter/py.typed
import_rewriter/rewrite.py
import_rewriter-1.0.0.dist-info/METADATA
import_rewriter-1.0.0.dist-info/WHEEL
import_rewriter-1.0.0.dist-info/licenses/LICENSE
import_rewriter-1.0.0.dist-info/RECORD
