Metadata-Version: 2.4
Name: import-rewriter
Version: 1.0.0
Summary: A flexible library for dynamically rewriting Python imports at runtime using metapath hooks.
Project-URL: Homepage, https://github.com/djcopley/import-rewriter
Project-URL: Repository, https://github.com/djcopley/import-rewriter.git
Project-URL: Issues, https://github.com/djcopley/import-rewriter/issues
Author-email: Daniel Copley <djcopley@proton.me>
License:                     GNU GENERAL PUBLIC LICENSE
License-File: LICENSE
Classifier: Development Status :: 5 - Production/Stable
Classifier: Environment :: Console
Classifier: Intended Audience :: Developers
Classifier: License :: OSI Approved :: GNU General Public License v3 (GPLv3)
Classifier: Operating System :: MacOS
Classifier: Operating System :: POSIX :: Linux
Classifier: Programming Language :: Python :: 3
Classifier: Programming Language :: Python :: 3.9
Classifier: Programming Language :: Python :: 3.10
Classifier: Programming Language :: Python :: 3.11
Classifier: Programming Language :: Python :: 3.12
Classifier: Programming Language :: Python :: 3.13
Requires-Python: >=3.9
Requires-Dist: astroid~=3.0
